quantumz/__init__.py
quantumz/main.py
quantumz/main_old.py
quantumz-0.0.5.dist-info/LICENSE
quantumz-0.0.5.dist-info/METADATA
quantumz-0.0.5.dist-info/WHEEL
quantumz-0.0.5.dist-info/top_level.txt
quantumz-0.0.5.dist-info/RECORD
