Metadata-Version: 2.1
Name: quantumz
Version: 0.0.5
Summary: A module for quantum computing emulations
Author: Sergei Zuev
Author-email: shoukhov@mail.ru
Classifier: Programming Language :: Python :: 3.10
Classifier: Operating System :: OS Independent
Requires-Python: >=3.6
License-File: LICENSE
